ocui/__init__.py
ocui/app.py
ocui/config.py
ocui/utils.py
ocui/oci/runtime.py
ocui/oci/command/__init__.py
ocui/oci/command/container.py
ocui/oci/command/image.py
ocui/oci/dataclass/container.py
ocui/oci/dataclass/image.py
ocui/oci/serialization/__init__.py
ocui/oci/serialization/container.py
ocui/oci/serialization/image.py
ocui/oci/serialization/solver.py
ocui/oci/serialization/utils.py
ocui/res/egg.b64
ocui/res/logo.txt
ocui/ui/adapters.py
ocui/ui/container.py
ocui/ui/image.py
ocui/ui/inspect.py
ocui/ui/run.py
ocui/ui/volume.py
ocui/ui/base/header.py
ocui/ui/base/screen.py
ocui/ui/base/utils.py
ocui/ui/base/css/body.tcss
ocui/ui/base/css/header.tcss
ocui/ui/base/css/inspect.tcss
ocui-0.1.1.dist-info/entry_points.txt
ocui-0.1.1.dist-info/LICENSE
ocui-0.1.1.dist-info/WHEEL
ocui-0.1.1.dist-info/METADATA
ocui-0.1.1.dist-info/RECORD
