Metadata-Version: 2.1
Name: ocui
Version: 0.1.1
Summary: ocui is a terminal user interface to facilitate the most common tasks around
Author-email: Giacomo Leidi <goodoldpaul@autistici.org>
Requires-Python: >=3.10
Requires-Dist: appdirs ~=1.4
Requires-Dist: textual ~=0.41
Requires-Dist: toml ~=0.10
Requires-Dist: flake8 ~=6.1 ; extra == "test"
Requires-Dist: debugpy ~=1.6 ; extra == "test"
Requires-Dist: textual-dev ~=1.2 ; extra == "test"
Project-URL: Home, https://github.com/fishinthecalculator/ocui
Provides-Extra: test
